django_cgi/__init__.py
django_cgi/apps.py
django_cgi/management/commands/generate_cgi_handler.py
django_cgi-0.1.2.dist-info/LICENSE
django_cgi-0.1.2.dist-info/WHEEL
django_cgi-0.1.2.dist-info/METADATA
django_cgi-0.1.2.dist-info/RECORD
