Metadata-Version: 2.1
Name: django-cgi
Version: 0.1.2
Summary: Run Django with CGI
Home-page: https://github.com/enricobarzetti/django-cgi
Author: Enrico Barzetti
Author-email: enricobarzetti@gmail.com
Requires-Python: >=3.8,<4.0
Classifier: Programming Language :: Python :: 3
Classifier: Programming Language :: Python :: 3.8
Requires-Dist: django (>=3.1,<4.0)
